README.rst
setup.py
vecnet/__init__.py
vecnet.simulation.egg-info/PKG-INFO
vecnet.simulation.egg-info/SOURCES.txt
vecnet.simulation.egg-info/dependency_links.txt
vecnet.simulation.egg-info/namespace_packages.txt
vecnet.simulation.egg-info/top_level.txt
vecnet/simulation/__init__.py
vecnet/simulation/sim_model.py
vecnet/simulation/sim_status.py
vecnet/simulation/submission_status.py
vecnet/tests/__init__.py
vecnet/tests/test_execution_request.py
vecnet/tests/test_sim_status.py
vecnet/tests/test_simulation.py
vecnet/tests/test_simulation_group.py
vecnet/tests/test_submission_status.py